nrv/__init__.py
nrv/_misc/NRV.ini
nrv/_misc/comsol_templates/Nerve_1_Fascicle_1_CUFF.mph
nrv/_misc/comsol_templates/Nerve_1_Fascicle_1_LIFE.mph
nrv/_misc/comsol_templates/Nerve_1_Fascicle_2_LIFE.mph
nrv/_misc/geom/smoothed_edges_white.dxf
nrv/_misc/geom/smoothed_edges_white.png
nrv/_misc/log/NRV.log
nrv/_misc/materials/axoplasmic_mrg.mat
nrv/_misc/materials/bone.mat
nrv/_misc/materials/cerebrospinal_fluid.mat
nrv/_misc/materials/dura.mat
nrv/_misc/materials/endoneurium_bhadra.mat
nrv/_misc/materials/endoneurium_horn.mat
nrv/_misc/materials/endoneurium_ranck.mat
nrv/_misc/materials/epidural_space.mat
nrv/_misc/materials/epineurium.mat
nrv/_misc/materials/epineurium_horn.mat
nrv/_misc/materials/material_1.mat
nrv/_misc/materials/material_2.mat
nrv/_misc/materials/muscle.mat
nrv/_misc/materials/perineurium.mat
nrv/_misc/materials/perineurium_horn.mat
nrv/_misc/materials/platinum.mat
nrv/_misc/materials/saline.mat
nrv/_misc/materials/silicone.mat
nrv/_misc/mods/AXNODE.mod
nrv/_misc/mods/CaPump.mod
nrv/_misc/mods/DNav18.mod
nrv/_misc/mods/KCa.mod
nrv/_misc/mods/NaCaPump.mod
nrv/_misc/mods/Nakpump.mod
nrv/_misc/mods/NakpumpSchild.mod
nrv/_misc/mods/Nav11_a.mod
nrv/_misc/mods/Nav16_a.mod
nrv/_misc/mods/RattayAberham.mod
nrv/_misc/mods/caextscale.mod
nrv/_misc/mods/caintscale.mod
nrv/_misc/mods/can.mod
nrv/_misc/mods/cat.mod
nrv/_misc/mods/extrapump.mod
nrv/_misc/mods/flut_motor.mod
nrv/_misc/mods/flut_sensory.mod
nrv/_misc/mods/h.mod
nrv/_misc/mods/k_ion_dynamics.mod
nrv/_misc/mods/ka.mod
nrv/_misc/mods/kaslow.mod
nrv/_misc/mods/kd.mod
nrv/_misc/mods/kdr.mod
nrv/_misc/mods/kdr_Tiger.mod
nrv/_misc/mods/kds.mod
nrv/_misc/mods/kf.mod
nrv/_misc/mods/kmtype.mod
nrv/_misc/mods/kna.mod
nrv/_misc/mods/ks.mod
nrv/_misc/mods/leak.mod
nrv/_misc/mods/leakSchild.mod
nrv/_misc/mods/mysa_motor.mod
nrv/_misc/mods/mysa_sensory.mod
nrv/_misc/mods/na3.mod
nrv/_misc/mods/na_ion_dynamics.mod
nrv/_misc/mods/naf.mod
nrv/_misc/mods/naf97.mod
nrv/_misc/mods/naf97mean.mod
nrv/_misc/mods/nahh.mod
nrv_py-1.3.1.dist-info/METADATA
nrv_py-1.3.1.dist-info/WHEEL
nrv_py-1.3.1.dist-info/top_level.txt
nrv_py-1.3.1.dist-info/RECORD
