Metadata-Version: 2.4
Name: nrv-py
Version: 1.3.1
Summary: NeuRon Virtualizer (NRV)
Home-page: https://github.com/nrv-framework/NRV
Author: Florian Kolbl, Roland Giraud, Louis Regnacq, Thomas Couppey
Classifier: Development Status :: 5 - Production/Stable
Classifier: Programming Language :: Python :: 3.10
Classifier: Programming Language :: Python :: 3.11
Classifier: Programming Language :: Python :: 3.12
Classifier: Operating System :: Microsoft :: Windows
Classifier: Operating System :: POSIX :: Linux
Classifier: Operating System :: MacOS :: MacOS X
Classifier: Intended Audience :: Education
Classifier: Intended Audience :: Science/Research
Classifier: Topic :: Scientific/Engineering :: Bio-Informatics
Classifier: Topic :: Scientific/Engineering :: Medical Science Apps.
Classifier: Natural Language :: English
Requires-Python: >=3.12
Requires-Dist: icecream
Requires-Dist: matplotlib
Requires-Dist: mph
Requires-Dist: neuron
Requires-Dist: numpy
Requires-Dist: pandas
Requires-Dist: pathos
Requires-Dist: psutil
Requires-Dist: pyeit
Requires-Dist: pyswarms
Requires-Dist: rich
Requires-Dist: scipy
Requires-Dist: seaborn
Requires-Dist: shapely
Dynamic: author
Dynamic: classifier
Dynamic: description
Dynamic: description-content-type
Dynamic: home-page
Dynamic: requires-dist
Dynamic: requires-python
Dynamic: summary
